{
  "generated_at": "2025-05-08 05:43:08",
  "forecast_days": 90,
  "forecasts": {
    "USD": [
      {
        "date": "2025-05-09",
        "prediction": 38.6854,
        "conf_low": 38.2983,
        "conf_high": 39.0725
      },
      {
        "date": "2025-05-10",
        "prediction": 38.7157,
        "conf_low": 38.1436,
        "conf_high": 39.2878
      },
      {
        "date": "2025-05-11",
        "prediction": 38.7326,
        "conf_low": 38.0189,
        "conf_high": 39.4463
      },
      {
        "date": "2025-05-12",
        "prediction": 38.7691,
        "conf_low": 37.9371,
        "conf_high": 39.6012
      },
      {
        "date": "2025-05-13",
        "prediction": 38.7952,
        "conf_low": 37.8596,
        "conf_high": 39.7308
      },
      {
        "date": "2025-05-14",
        "prediction": 38.8302,
        "conf_low": 37.8015,
        "conf_high": 39.859
      },
      {
        "date": "2025-05-15",
        "prediction": 38.8759,
        "conf_low": 37.7617,
        "conf_high": 39.9901
      },
      {
        "date": "2025-05-16",
        "prediction": 38.9056,
        "conf_low": 37.7121,
        "conf_high": 40.0991
      },
      {
        "date": "2025-05-17",
        "prediction": 38.9257,
        "conf_low": 37.6578,
        "conf_high": 40.1936
      },
      {
        "date": "2025-05-18",
        "prediction": 38.9416,
        "conf_low": 37.6035,
        "conf_high": 40.2797
      },
      {
        "date": "2025-05-19",
        "prediction": 38.9489,
        "conf_low": 37.544,
        "conf_high": 40.3537
      },
      {
        "date": "2025-05-20",
        "prediction": 38.9401,
        "conf_low": 37.4716,
        "conf_high": 40.4087
      },
      {
        "date": "2025-05-21",
        "prediction": 39.0085,
        "conf_low": 37.4789,
        "conf_high": 40.5381
      },
      {
        "date": "2025-05-22",
        "prediction": 39.0509,
        "conf_low": 37.4626,
        "conf_high": 40.6392
      },
      {
        "date": "2025-05-23",
        "prediction": 39.0785,
        "conf_low": 37.4336,
        "conf_high": 40.7234
      },
      {
        "date": "2025-05-24",
        "prediction": 39.1256,
        "conf_low": 37.4259,
        "conf_high": 40.8252
      },
      {
        "date": "2025-05-25",
        "prediction": 39.1655,
        "conf_low": 37.4129,
        "conf_high": 40.9182
      },
      {
        "date": "2025-05-26",
        "prediction": 39.2185,
        "conf_low": 37.4144,
        "conf_high": 41.0227
      },
      {
        "date": "2025-05-27",
        "prediction": 39.2726,
        "conf_low": 37.4184,
        "conf_high": 41.1268
      },
      {
        "date": "2025-05-28",
        "prediction": 39.3202,
        "conf_low": 37.4173,
        "conf_high": 41.2231
      },
      {
        "date": "2025-05-29",
        "prediction": 39.2204,
        "conf_low": 37.27,
        "conf_high": 41.1707
      },
      {
        "date": "2025-05-30",
        "prediction": 39.2326,
        "conf_low": 37.2359,
        "conf_high": 41.2293
      },
      {
        "date": "2025-05-31",
        "prediction": 39.2143,
        "conf_low": 37.1723,
        "conf_high": 41.2563
      },
      {
        "date": "2025-06-01",
        "prediction": 39.2314,
        "conf_low": 37.1451,
        "conf_high": 41.3177
      },
      {
        "date": "2025-06-02",
        "prediction": 39.2304,
        "conf_low": 37.1007,
        "conf_high": 41.3601
      },
      {
        "date": "2025-06-03",
        "prediction": 39.2785,
        "conf_low": 37.1063,
        "conf_high": 41.4507
      },
      {
        "date": "2025-06-04",
        "prediction": 39.33,
        "conf_low": 37.1161,
        "conf_high": 41.5439
      },
      {
        "date": "2025-06-05",
        "prediction": 39.3822,
        "conf_low": 37.1273,
        "conf_high": 41.637
      },
      {
        "date": "2025-06-06",
        "prediction": 39.461,
        "conf_low": 37.166,
        "conf_high": 41.7561
      },
      {
        "date": "2025-06-07",
        "prediction": 39.4914,
        "conf_low": 37.1568,
        "conf_high": 41.8259
      },
      {
        "date": "2025-06-08",
        "prediction": 39.5498,
        "conf_low": 37.1755,
        "conf_high": 41.9241
      },
      {
        "date": "2025-06-09",
        "prediction": 39.5799,
        "conf_low": 37.1664,
        "conf_high": 41.9934
      },
      {
        "date": "2025-06-10",
        "prediction": 39.5973,
        "conf_low": 37.1452,
        "conf_high": 42.0493
      },
      {
        "date": "2025-06-11",
        "prediction": 39.6335,
        "conf_low": 37.1435,
        "conf_high": 42.1236
      },
      {
        "date": "2025-06-12",
        "prediction": 39.6593,
        "conf_low": 37.1318,
        "conf_high": 42.1868
      },
      {
        "date": "2025-06-13",
        "prediction": 39.6914,
        "conf_low": 37.127,
        "conf_high": 42.2557
      },
      {
        "date": "2025-06-14",
        "prediction": 39.7377,
        "conf_low": 37.137,
        "conf_high": 42.3384
      },
      {
        "date": "2025-06-15",
        "prediction": 39.767,
        "conf_low": 37.1305,
        "conf_high": 42.4036
      },
      {
        "date": "2025-06-16",
        "prediction": 39.7866,
        "conf_low": 37.1148,
        "conf_high": 42.4585
      },
      {
        "date": "2025-06-17",
        "prediction": 39.8036,
        "conf_low": 37.0968,
        "conf_high": 42.5103
      },
      {
        "date": "2025-06-18",
        "prediction": 39.8107,
        "conf_low": 37.0695,
        "conf_high": 42.5519
      },
      {
        "date": "2025-06-19",
        "prediction": 39.8021,
        "conf_low": 37.0269,
        "conf_high": 42.5774
      },
      {
        "date": "2025-06-20",
        "prediction": 39.8684,
        "conf_low": 37.0596,
        "conf_high": 42.6773
      },
      {
        "date": "2025-06-21",
        "prediction": 39.9109,
        "conf_low": 37.0688,
        "conf_high": 42.753
      },
      {
        "date": "2025-06-22",
        "prediction": 39.9389,
        "conf_low": 37.064,
        "conf_high": 42.8138
      },
      {
        "date": "2025-06-23",
        "prediction": 39.9859,
        "conf_low": 37.0785,
        "conf_high": 42.8933
      },
      {
        "date": "2025-06-24",
        "prediction": 40.0259,
        "conf_low": 37.0864,
        "conf_high": 42.9654
      },
      {
        "date": "2025-06-25",
        "prediction": 40.0783,
        "conf_low": 37.1071,
        "conf_high": 43.0496
      },
      {
        "date": "2025-06-26",
        "prediction": 40.1307,
        "conf_low": 37.1281,
        "conf_high": 43.1334
      },
      {
        "date": "2025-06-27",
        "prediction": 40.1792,
        "conf_low": 37.1455,
        "conf_high": 43.213
      },
      {
        "date": "2025-06-28",
        "prediction": 40.0811,
        "conf_low": 37.0167,
        "conf_high": 43.1456
      },
      {
        "date": "2025-06-29",
        "prediction": 40.0947,
        "conf_low": 36.9998,
        "conf_high": 43.1896
      },
      {
        "date": "2025-06-30",
        "prediction": 40.0768,
        "conf_low": 36.9518,
        "conf_high": 43.2018
      },
      {
        "date": "2025-07-01",
        "prediction": 40.0955,
        "conf_low": 36.9407,
        "conf_high": 43.2503
      },
      {
        "date": "2025-07-02",
        "prediction": 40.0945,
        "conf_low": 36.9101,
        "conf_high": 43.2789
      },
      {
        "date": "2025-07-03",
        "prediction": 40.1419,
        "conf_low": 36.9282,
        "conf_high": 43.3555
      },
      {
        "date": "2025-07-04",
        "prediction": 40.1927,
        "conf_low": 36.95,
        "conf_high": 43.4353
      },
      {
        "date": "2025-07-05",
        "prediction": 40.2462,
        "conf_low": 36.9747,
        "conf_high": 43.5176
      },
      {
        "date": "2025-07-06",
        "prediction": 40.3241,
        "conf_low": 37.0242,
        "conf_high": 43.624
      },
      {
        "date": "2025-07-07",
        "prediction": 40.3544,
        "conf_low": 37.0262,
        "conf_high": 43.6826
      },
      {
        "date": "2025-07-08",
        "prediction": 40.4129,
        "conf_low": 37.0553,
        "conf_high": 43.7705
      },
      {
        "date": "2025-07-09",
        "prediction": 40.443,
        "conf_low": 37.0561,
        "conf_high": 43.8299
      },
      {
        "date": "2025-07-10",
        "prediction": 40.4603,
        "conf_low": 37.0444,
        "conf_high": 43.8763
      },
      {
        "date": "2025-07-11",
        "prediction": 40.4966,
        "conf_low": 37.0519,
        "conf_high": 43.9414
      },
      {
        "date": "2025-07-12",
        "prediction": 40.5224,
        "conf_low": 37.049,
        "conf_high": 43.9957
      },
      {
        "date": "2025-07-13",
        "prediction": 40.5545,
        "conf_low": 37.0528,
        "conf_high": 44.0562
      },
      {
        "date": "2025-07-14",
        "prediction": 40.6008,
        "conf_low": 37.071,
        "conf_high": 44.1306
      },
      {
        "date": "2025-07-15",
        "prediction": 40.6302,
        "conf_low": 37.0725,
        "conf_high": 44.1878
      },
      {
        "date": "2025-07-16",
        "prediction": 40.6498,
        "conf_low": 37.0644,
        "conf_high": 44.2351
      },
      {
        "date": "2025-07-17",
        "prediction": 40.6667,
        "conf_low": 37.0539,
        "conf_high": 44.2795
      },
      {
        "date": "2025-07-18",
        "prediction": 40.6738,
        "conf_low": 37.0337,
        "conf_high": 44.3139
      },
      {
        "date": "2025-07-19",
        "prediction": 40.6652,
        "conf_low": 36.9981,
        "conf_high": 44.3324
      },
      {
        "date": "2025-07-20",
        "prediction": 40.7316,
        "conf_low": 37.0376,
        "conf_high": 44.4255
      },
      {
        "date": "2025-07-21",
        "prediction": 40.7741,
        "conf_low": 37.0534,
        "conf_high": 44.4947
      },
      {
        "date": "2025-07-22",
        "prediction": 40.802,
        "conf_low": 37.0549,
        "conf_high": 44.5491
      },
      {
        "date": "2025-07-23",
        "prediction": 40.8491,
        "conf_low": 37.0757,
        "conf_high": 44.6224
      },
      {
        "date": "2025-07-24",
        "prediction": 40.889,
        "conf_low": 37.0895,
        "conf_high": 44.6885
      },
      {
        "date": "2025-07-25",
        "prediction": 40.9415,
        "conf_low": 37.1161,
        "conf_high": 44.7669
      },
      {
        "date": "2025-07-26",
        "prediction": 40.9939,
        "conf_low": 37.1428,
        "conf_high": 44.8451
      },
      {
        "date": "2025-07-27",
        "prediction": 41.0424,
        "conf_low": 37.1657,
        "conf_high": 44.9191
      },
      {
        "date": "2025-07-28",
        "prediction": 40.9443,
        "conf_low": 37.0422,
        "conf_high": 44.8463
      },
      {
        "date": "2025-07-29",
        "prediction": 40.9578,
        "conf_low": 37.0306,
        "conf_high": 44.885
      },
      {
        "date": "2025-07-30",
        "prediction": 40.9399,
        "conf_low": 36.9877,
        "conf_high": 44.8922
      },
      {
        "date": "2025-07-31",
        "prediction": 40.9586,
        "conf_low": 36.9815,
        "conf_high": 44.9356
      },
      {
        "date": "2025-08-01",
        "prediction": 40.9576,
        "conf_low": 36.9558,
        "conf_high": 44.9594
      },
      {
        "date": "2025-08-02",
        "prediction": 41.005,
        "conf_low": 36.9787,
        "conf_high": 45.0313
      },
      {
        "date": "2025-08-03",
        "prediction": 41.0558,
        "conf_low": 37.0051,
        "conf_high": 45.1065
      },
      {
        "date": "2025-08-04",
        "prediction": 41.1092,
        "conf_low": 37.0343,
        "conf_high": 45.1842
      },
      {
        "date": "2025-08-05",
        "prediction": 41.1872,
        "conf_low": 37.0881,
        "conf_high": 45.2863
      },
      {
        "date": "2025-08-06",
        "prediction": 41.2175,
        "conf_low": 37.0945,
        "conf_high": 45.3406
      }
    ],
    "EUR": [
      {
        "date": "2025-05-09",
        "prediction": 43.9616,
        "conf_low": 43.4811,
        "conf_high": 44.4422
      },
      {
        "date": "2025-05-10",
        "prediction": 44.0298,
        "conf_low": 43.3167,
        "conf_high": 44.7428
      },
      {
        "date": "2025-05-11",
        "prediction": 44.0306,
        "conf_low": 43.1413,
        "conf_high": 44.9199
      },
      {
        "date": "2025-05-12",
        "prediction": 44.0696,
        "conf_low": 43.0334,
        "conf_high": 45.1058
      },
      {
        "date": "2025-05-13",
        "prediction": 44.1037,
        "conf_low": 42.9389,
        "conf_high": 45.2684
      },
      {
        "date": "2025-05-14",
        "prediction": 44.1287,
        "conf_low": 42.8482,
        "conf_high": 45.4092
      },
      {
        "date": "2025-05-15",
        "prediction": 44.1601,
        "conf_low": 42.7735,
        "conf_high": 45.5467
      },
      {
        "date": "2025-05-16",
        "prediction": 44.2151,
        "conf_low": 42.73,
        "conf_high": 45.7002
      },
      {
        "date": "2025-05-17",
        "prediction": 44.2143,
        "conf_low": 42.6367,
        "conf_high": 45.7918
      },
      {
        "date": "2025-05-18",
        "prediction": 44.2327,
        "conf_low": 42.5679,
        "conf_high": 45.8975
      },
      {
        "date": "2025-05-19",
        "prediction": 44.2315,
        "conf_low": 42.4838,
        "conf_high": 45.9792
      },
      {
        "date": "2025-05-20",
        "prediction": 44.1959,
        "conf_low": 42.369,
        "conf_high": 46.0227
      },
      {
        "date": "2025-05-21",
        "prediction": 44.288,
        "conf_low": 42.3853,
        "conf_high": 46.1907
      },
      {
        "date": "2025-05-22",
        "prediction": 44.3506,
        "conf_low": 42.3749,
        "conf_high": 46.3263
      },
      {
        "date": "2025-05-23",
        "prediction": 44.3668,
        "conf_low": 42.3207,
        "conf_high": 46.4128
      },
      {
        "date": "2025-05-24",
        "prediction": 44.3841,
        "conf_low": 42.27,
        "conf_high": 46.4982
      },
      {
        "date": "2025-05-25",
        "prediction": 44.4402,
        "conf_low": 42.2603,
        "conf_high": 46.6202
      },
      {
        "date": "2025-05-26",
        "prediction": 44.526,
        "conf_low": 42.2821,
        "conf_high": 46.7699
      },
      {
        "date": "2025-05-27",
        "prediction": 44.601,
        "conf_low": 42.2949,
        "conf_high": 46.9071
      },
      {
        "date": "2025-05-28",
        "prediction": 44.6657,
        "conf_low": 42.299,
        "conf_high": 47.0324
      },
      {
        "date": "2025-05-29",
        "prediction": 44.5781,
        "conf_low": 42.1524,
        "conf_high": 47.0037
      },
      {
        "date": "2025-05-30",
        "prediction": 44.611,
        "conf_low": 42.1277,
        "conf_high": 47.0942
      },
      {
        "date": "2025-05-31",
        "prediction": 44.5891,
        "conf_low": 42.0495,
        "conf_high": 47.1286
      },
      {
        "date": "2025-06-01",
        "prediction": 44.615,
        "conf_low": 42.0203,
        "conf_high": 47.2096
      },
      {
        "date": "2025-06-02",
        "prediction": 44.6082,
        "conf_low": 41.9596,
        "conf_high": 47.2568
      },
      {
        "date": "2025-06-03",
        "prediction": 44.6551,
        "conf_low": 41.9537,
        "conf_high": 47.3565
      },
      {
        "date": "2025-06-04",
        "prediction": 44.7016,
        "conf_low": 41.9484,
        "conf_high": 47.4549
      },
      {
        "date": "2025-06-05",
        "prediction": 44.7775,
        "conf_low": 41.9734,
        "conf_high": 47.5816
      },
      {
        "date": "2025-06-06",
        "prediction": 44.8476,
        "conf_low": 41.9935,
        "conf_high": 47.7017
      },
      {
        "date": "2025-06-07",
        "prediction": 44.8483,
        "conf_low": 41.9451,
        "conf_high": 47.7515
      },
      {
        "date": "2025-06-08",
        "prediction": 44.9028,
        "conf_low": 41.95,
        "conf_high": 47.8557
      },
      {
        "date": "2025-06-09",
        "prediction": 44.9687,
        "conf_low": 41.967,
        "conf_high": 47.9705
      },
      {
        "date": "2025-06-10",
        "prediction": 44.9682,
        "conf_low": 41.9183,
        "conf_high": 48.0181
      },
      {
        "date": "2025-06-11",
        "prediction": 45.0066,
        "conf_low": 41.9093,
        "conf_high": 48.1039
      },
      {
        "date": "2025-06-12",
        "prediction": 45.0395,
        "conf_low": 41.8955,
        "conf_high": 48.1834
      },
      {
        "date": "2025-06-13",
        "prediction": 45.062,
        "conf_low": 41.872,
        "conf_high": 48.252
      },
      {
        "date": "2025-06-14",
        "prediction": 45.0952,
        "conf_low": 41.8599,
        "conf_high": 48.3306
      },
      {
        "date": "2025-06-15",
        "prediction": 45.1603,
        "conf_low": 41.8802,
        "conf_high": 48.4403
      },
      {
        "date": "2025-06-16",
        "prediction": 45.1591,
        "conf_low": 41.8349,
        "conf_high": 48.4833
      },
      {
        "date": "2025-06-17",
        "prediction": 45.1766,
        "conf_low": 41.8089,
        "conf_high": 48.5444
      },
      {
        "date": "2025-06-18",
        "prediction": 45.1732,
        "conf_low": 41.7625,
        "conf_high": 48.5839
      },
      {
        "date": "2025-06-19",
        "prediction": 45.1429,
        "conf_low": 41.6898,
        "conf_high": 48.5961
      },
      {
        "date": "2025-06-20",
        "prediction": 45.2332,
        "conf_low": 41.7381,
        "conf_high": 48.7283
      },
      {
        "date": "2025-06-21",
        "prediction": 45.3104,
        "conf_low": 41.7738,
        "conf_high": 48.8469
      },
      {
        "date": "2025-06-22",
        "prediction": 45.3289,
        "conf_low": 41.7514,
        "conf_high": 48.9064
      },
      {
        "date": "2025-06-23",
        "prediction": 45.3442,
        "conf_low": 41.7262,
        "conf_high": 48.9622
      },
      {
        "date": "2025-06-24",
        "prediction": 45.4014,
        "conf_low": 41.7434,
        "conf_high": 49.0594
      },
      {
        "date": "2025-06-25",
        "prediction": 45.4863,
        "conf_low": 41.7887,
        "conf_high": 49.184
      },
      {
        "date": "2025-06-26",
        "prediction": 45.5598,
        "conf_low": 41.823,
        "conf_high": 49.2966
      },
      {
        "date": "2025-06-27",
        "prediction": 45.6333,
        "conf_low": 41.8577,
        "conf_high": 49.4089
      },
      {
        "date": "2025-06-28",
        "prediction": 45.5449,
        "conf_low": 41.7309,
        "conf_high": 49.3588
      },
      {
        "date": "2025-06-29",
        "prediction": 45.573,
        "conf_low": 41.7211,
        "conf_high": 49.4248
      },
      {
        "date": "2025-06-30",
        "prediction": 45.5505,
        "conf_low": 41.6611,
        "conf_high": 49.4399
      },
      {
        "date": "2025-07-01",
        "prediction": 45.5775,
        "conf_low": 41.6509,
        "conf_high": 49.5041
      },
      {
        "date": "2025-07-02",
        "prediction": 45.5728,
        "conf_low": 41.6093,
        "conf_high": 49.5362
      },
      {
        "date": "2025-07-03",
        "prediction": 45.6185,
        "conf_low": 41.6185,
        "conf_high": 49.6184
      },
      {
        "date": "2025-07-04",
        "prediction": 45.6627,
        "conf_low": 41.6265,
        "conf_high": 49.6988
      },
      {
        "date": "2025-07-05",
        "prediction": 45.7394,
        "conf_low": 41.6674,
        "conf_high": 49.8115
      },
      {
        "date": "2025-07-06",
        "prediction": 45.8086,
        "conf_low": 41.701,
        "conf_high": 49.9162
      },
      {
        "date": "2025-07-07",
        "prediction": 45.8114,
        "conf_low": 41.6686,
        "conf_high": 49.9542
      },
      {
        "date": "2025-07-08",
        "prediction": 45.8662,
        "conf_low": 41.6867,
        "conf_high": 50.0457
      },
      {
        "date": "2025-07-09",
        "prediction": 45.9321,
        "conf_low": 41.7161,
        "conf_high": 50.1481
      },
      {
        "date": "2025-07-10",
        "prediction": 45.9316,
        "conf_low": 41.6794,
        "conf_high": 50.1838
      },
      {
        "date": "2025-07-11",
        "prediction": 45.97,
        "conf_low": 41.6818,
        "conf_high": 50.2581
      },
      {
        "date": "2025-07-12",
        "prediction": 46.0029,
        "conf_low": 41.6791,
        "conf_high": 50.3266
      },
      {
        "date": "2025-07-13",
        "prediction": 46.0255,
        "conf_low": 41.6664,
        "conf_high": 50.3845
      },
      {
        "date": "2025-07-14",
        "prediction": 46.0587,
        "conf_low": 41.6646,
        "conf_high": 50.4528
      },
      {
        "date": "2025-07-15",
        "prediction": 46.1236,
        "conf_low": 41.6947,
        "conf_high": 50.5525
      },
      {
        "date": "2025-07-16",
        "prediction": 46.1224,
        "conf_low": 41.6591,
        "conf_high": 50.5858
      },
      {
        "date": "2025-07-17",
        "prediction": 46.14,
        "conf_low": 41.6424,
        "conf_high": 50.6376
      },
      {
        "date": "2025-07-18",
        "prediction": 46.1366,
        "conf_low": 41.605,
        "conf_high": 50.6682
      },
      {
        "date": "2025-07-19",
        "prediction": 46.1062,
        "conf_low": 41.5409,
        "conf_high": 50.6715
      },
      {
        "date": "2025-07-20",
        "prediction": 46.1965,
        "conf_low": 41.5978,
        "conf_high": 50.7953
      },
      {
        "date": "2025-07-21",
        "prediction": 46.2735,
        "conf_low": 41.6415,
        "conf_high": 50.9055
      },
      {
        "date": "2025-07-22",
        "prediction": 46.292,
        "conf_low": 41.6271,
        "conf_high": 50.957
      },
      {
        "date": "2025-07-23",
        "prediction": 46.3073,
        "conf_low": 41.6096,
        "conf_high": 51.005
      },
      {
        "date": "2025-07-24",
        "prediction": 46.3645,
        "conf_low": 41.6343,
        "conf_high": 51.0948
      },
      {
        "date": "2025-07-25",
        "prediction": 46.4494,
        "conf_low": 41.6869,
        "conf_high": 51.212
      },
      {
        "date": "2025-07-26",
        "prediction": 46.5229,
        "conf_low": 41.7283,
        "conf_high": 51.3176
      },
      {
        "date": "2025-07-27",
        "prediction": 46.5963,
        "conf_low": 41.7698,
        "conf_high": 51.4229
      },
      {
        "date": "2025-07-28",
        "prediction": 46.5079,
        "conf_low": 41.6498,
        "conf_high": 51.366
      },
      {
        "date": "2025-07-29",
        "prediction": 46.5361,
        "conf_low": 41.6466,
        "conf_high": 51.4255
      },
      {
        "date": "2025-07-30",
        "prediction": 46.5136,
        "conf_low": 41.593,
        "conf_high": 51.4342
      },
      {
        "date": "2025-07-31",
        "prediction": 46.5406,
        "conf_low": 41.589,
        "conf_high": 51.4922
      },
      {
        "date": "2025-08-01",
        "prediction": 46.5358,
        "conf_low": 41.5535,
        "conf_high": 51.5182
      },
      {
        "date": "2025-08-02",
        "prediction": 46.5815,
        "conf_low": 41.5686,
        "conf_high": 51.5945
      },
      {
        "date": "2025-08-03",
        "prediction": 46.6258,
        "conf_low": 41.5824,
        "conf_high": 51.6691
      },
      {
        "date": "2025-08-04",
        "prediction": 46.7025,
        "conf_low": 41.629,
        "conf_high": 51.7761
      },
      {
        "date": "2025-08-05",
        "prediction": 46.7717,
        "conf_low": 41.6681,
        "conf_high": 51.8753
      },
      {
        "date": "2025-08-06",
        "prediction": 46.7745,
        "conf_low": 41.641,
        "conf_high": 51.908
      }
    ]
  }
}