{
  "generated_at": "2026-07-19 07:15:39",
  "forecast_days": 90,
  "forecasts": {
    "USD": [
      {
        "date": "2026-07-18",
        "prediction": 47.0715,
        "conf_low": 46.9199,
        "conf_high": 47.2232
      },
      {
        "date": "2026-07-19",
        "prediction": 47.1633,
        "conf_low": 46.9504,
        "conf_high": 47.3762
      },
      {
        "date": "2026-07-20",
        "prediction": 47.1765,
        "conf_low": 46.9172,
        "conf_high": 47.4357
      },
      {
        "date": "2026-07-21",
        "prediction": 47.1772,
        "conf_low": 46.8792,
        "conf_high": 47.4751
      },
      {
        "date": "2026-07-22",
        "prediction": 47.1999,
        "conf_low": 46.8681,
        "conf_high": 47.5317
      },
      {
        "date": "2026-07-23",
        "prediction": 47.2408,
        "conf_low": 46.8785,
        "conf_high": 47.603
      },
      {
        "date": "2026-07-24",
        "prediction": 47.2772,
        "conf_low": 46.8869,
        "conf_high": 47.6674
      },
      {
        "date": "2026-07-25",
        "prediction": 47.2937,
        "conf_low": 46.8775,
        "conf_high": 47.7099
      },
      {
        "date": "2026-07-26",
        "prediction": 47.3222,
        "conf_low": 46.8816,
        "conf_high": 47.7627
      },
      {
        "date": "2026-07-27",
        "prediction": 47.3465,
        "conf_low": 46.8829,
        "conf_high": 47.8101
      },
      {
        "date": "2026-07-28",
        "prediction": 47.3668,
        "conf_low": 46.8813,
        "conf_high": 47.8523
      },
      {
        "date": "2026-07-29",
        "prediction": 47.4009,
        "conf_low": 46.8945,
        "conf_high": 47.9074
      },
      {
        "date": "2026-07-30",
        "prediction": 47.4397,
        "conf_low": 46.9132,
        "conf_high": 47.9662
      },
      {
        "date": "2026-07-31",
        "prediction": 47.4698,
        "conf_low": 46.9239,
        "conf_high": 48.0157
      },
      {
        "date": "2026-08-01",
        "prediction": 47.4741,
        "conf_low": 46.9096,
        "conf_high": 48.0387
      },
      {
        "date": "2026-08-02",
        "prediction": 47.5026,
        "conf_low": 46.92,
        "conf_high": 48.0852
      },
      {
        "date": "2026-08-03",
        "prediction": 47.5412,
        "conf_low": 46.9411,
        "conf_high": 48.1414
      },
      {
        "date": "2026-08-04",
        "prediction": 47.5531,
        "conf_low": 46.9359,
        "conf_high": 48.1703
      },
      {
        "date": "2026-08-05",
        "prediction": 47.5745,
        "conf_low": 46.9408,
        "conf_high": 48.2082
      },
      {
        "date": "2026-08-06",
        "prediction": 47.5996,
        "conf_low": 46.9497,
        "conf_high": 48.2495
      },
      {
        "date": "2026-08-07",
        "prediction": 47.6178,
        "conf_low": 46.9522,
        "conf_high": 48.2834
      },
      {
        "date": "2026-08-08",
        "prediction": 47.652,
        "conf_low": 46.971,
        "conf_high": 48.333
      },
      {
        "date": "2026-08-09",
        "prediction": 47.6997,
        "conf_low": 47.0036,
        "conf_high": 48.3958
      },
      {
        "date": "2026-08-10",
        "prediction": 47.7263,
        "conf_low": 47.0155,
        "conf_high": 48.4371
      },
      {
        "date": "2026-08-11",
        "prediction": 47.7613,
        "conf_low": 47.036,
        "conf_high": 48.4865
      },
      {
        "date": "2026-08-12",
        "prediction": 47.7684,
        "conf_low": 47.029,
        "conf_high": 48.5077
      },
      {
        "date": "2026-08-13",
        "prediction": 47.8012,
        "conf_low": 47.048,
        "conf_high": 48.5545
      },
      {
        "date": "2026-08-14",
        "prediction": 47.8373,
        "conf_low": 47.0704,
        "conf_high": 48.6042
      },
      {
        "date": "2026-08-15",
        "prediction": 47.8485,
        "conf_low": 47.0682,
        "conf_high": 48.6287
      },
      {
        "date": "2026-08-16",
        "prediction": 47.8848,
        "conf_low": 47.0913,
        "conf_high": 48.6782
      },
      {
        "date": "2026-08-17",
        "prediction": 47.9052,
        "conf_low": 47.0977,
        "conf_high": 48.7127
      },
      {
        "date": "2026-08-18",
        "prediction": 47.9971,
        "conf_low": 47.1758,
        "conf_high": 48.8184
      },
      {
        "date": "2026-08-19",
        "prediction": 48.011,
        "conf_low": 47.1762,
        "conf_high": 48.8459
      },
      {
        "date": "2026-08-20",
        "prediction": 48.012,
        "conf_low": 47.1638,
        "conf_high": 48.8602
      },
      {
        "date": "2026-08-21",
        "prediction": 48.0349,
        "conf_low": 47.1735,
        "conf_high": 48.8962
      },
      {
        "date": "2026-08-22",
        "prediction": 48.0758,
        "conf_low": 47.2015,
        "conf_high": 48.95
      },
      {
        "date": "2026-08-23",
        "prediction": 48.1122,
        "conf_low": 47.2252,
        "conf_high": 48.9992
      },
      {
        "date": "2026-08-24",
        "prediction": 48.1291,
        "conf_low": 47.2296,
        "conf_high": 49.0286
      },
      {
        "date": "2026-08-25",
        "prediction": 48.1576,
        "conf_low": 47.2458,
        "conf_high": 49.0694
      },
      {
        "date": "2026-08-26",
        "prediction": 48.1819,
        "conf_low": 47.258,
        "conf_high": 49.1059
      },
      {
        "date": "2026-08-27",
        "prediction": 48.2023,
        "conf_low": 47.2663,
        "conf_high": 49.1382
      },
      {
        "date": "2026-08-28",
        "prediction": 48.2364,
        "conf_low": 47.2886,
        "conf_high": 49.1841
      },
      {
        "date": "2026-08-29",
        "prediction": 48.2754,
        "conf_low": 47.3159,
        "conf_high": 49.2349
      },
      {
        "date": "2026-08-30",
        "prediction": 48.3054,
        "conf_low": 47.3344,
        "conf_high": 49.2765
      },
      {
        "date": "2026-08-31",
        "prediction": 48.3098,
        "conf_low": 47.3274,
        "conf_high": 49.2923
      },
      {
        "date": "2026-09-01",
        "prediction": 48.3383,
        "conf_low": 47.3445,
        "conf_high": 49.332
      },
      {
        "date": "2026-09-02",
        "prediction": 48.3768,
        "conf_low": 47.3719,
        "conf_high": 49.3817
      },
      {
        "date": "2026-09-03",
        "prediction": 48.3891,
        "conf_low": 47.3732,
        "conf_high": 49.405
      },
      {
        "date": "2026-09-04",
        "prediction": 48.4105,
        "conf_low": 47.3836,
        "conf_high": 49.4373
      },
      {
        "date": "2026-09-05",
        "prediction": 48.4355,
        "conf_low": 47.3979,
        "conf_high": 49.4731
      },
      {
        "date": "2026-09-06",
        "prediction": 48.4537,
        "conf_low": 47.4054,
        "conf_high": 49.5021
      },
      {
        "date": "2026-09-07",
        "prediction": 48.4879,
        "conf_low": 47.429,
        "conf_high": 49.5468
      },
      {
        "date": "2026-09-08",
        "prediction": 48.5358,
        "conf_low": 47.4664,
        "conf_high": 49.6052
      },
      {
        "date": "2026-09-09",
        "prediction": 48.5623,
        "conf_low": 47.4826,
        "conf_high": 49.6421
      },
      {
        "date": "2026-09-10",
        "prediction": 48.5973,
        "conf_low": 47.5073,
        "conf_high": 49.6873
      },
      {
        "date": "2026-09-11",
        "prediction": 48.6044,
        "conf_low": 47.5042,
        "conf_high": 49.7046
      },
      {
        "date": "2026-09-12",
        "prediction": 48.6372,
        "conf_low": 47.5269,
        "conf_high": 49.7475
      },
      {
        "date": "2026-09-13",
        "prediction": 48.6735,
        "conf_low": 47.5533,
        "conf_high": 49.7938
      },
      {
        "date": "2026-09-14",
        "prediction": 48.6847,
        "conf_low": 47.5546,
        "conf_high": 49.8149
      },
      {
        "date": "2026-09-15",
        "prediction": 48.7211,
        "conf_low": 47.5811,
        "conf_high": 49.8611
      },
      {
        "date": "2026-09-16",
        "prediction": 48.7415,
        "conf_low": 47.5909,
        "conf_high": 49.8921
      },
      {
        "date": "2026-09-17",
        "prediction": 48.8334,
        "conf_low": 47.6723,
        "conf_high": 49.9946
      },
      {
        "date": "2026-09-18",
        "prediction": 48.8473,
        "conf_low": 47.6758,
        "conf_high": 50.0188
      },
      {
        "date": "2026-09-19",
        "prediction": 48.8483,
        "conf_low": 47.6665,
        "conf_high": 50.0301
      },
      {
        "date": "2026-09-20",
        "prediction": 48.8712,
        "conf_low": 47.6791,
        "conf_high": 50.0632
      },
      {
        "date": "2026-09-21",
        "prediction": 48.9121,
        "conf_low": 47.7099,
        "conf_high": 50.1142
      },
      {
        "date": "2026-09-22",
        "prediction": 48.9485,
        "conf_low": 47.7363,
        "conf_high": 50.1607
      },
      {
        "date": "2026-09-23",
        "prediction": 48.9654,
        "conf_low": 47.7432,
        "conf_high": 50.1876
      },
      {
        "date": "2026-09-24",
        "prediction": 48.9939,
        "conf_low": 47.7619,
        "conf_high": 50.2259
      },
      {
        "date": "2026-09-25",
        "prediction": 49.0182,
        "conf_low": 47.7765,
        "conf_high": 50.2599
      },
      {
        "date": "2026-09-26",
        "prediction": 49.0385,
        "conf_low": 47.7872,
        "conf_high": 50.2899
      },
      {
        "date": "2026-09-27",
        "prediction": 49.0726,
        "conf_low": 47.8118,
        "conf_high": 50.3335
      },
      {
        "date": "2026-09-28",
        "prediction": 49.1117,
        "conf_low": 47.8413,
        "conf_high": 50.3821
      },
      {
        "date": "2026-09-29",
        "prediction": 49.1417,
        "conf_low": 47.8619,
        "conf_high": 50.4215
      },
      {
        "date": "2026-09-30",
        "prediction": 49.1461,
        "conf_low": 47.8569,
        "conf_high": 50.4353
      },
      {
        "date": "2026-10-01",
        "prediction": 49.1746,
        "conf_low": 47.8761,
        "conf_high": 50.473
      },
      {
        "date": "2026-10-02",
        "prediction": 49.2131,
        "conf_low": 47.9055,
        "conf_high": 50.5208
      },
      {
        "date": "2026-10-03",
        "prediction": 49.2254,
        "conf_low": 47.9086,
        "conf_high": 50.5422
      },
      {
        "date": "2026-10-04",
        "prediction": 49.2468,
        "conf_low": 47.9209,
        "conf_high": 50.5727
      },
      {
        "date": "2026-10-05",
        "prediction": 49.2718,
        "conf_low": 47.9369,
        "conf_high": 50.6067
      },
      {
        "date": "2026-10-06",
        "prediction": 49.29,
        "conf_low": 47.9461,
        "conf_high": 50.6339
      },
      {
        "date": "2026-10-07",
        "prediction": 49.3242,
        "conf_low": 47.9714,
        "conf_high": 50.677
      },
      {
        "date": "2026-10-08",
        "prediction": 49.3721,
        "conf_low": 48.0104,
        "conf_high": 50.7337
      },
      {
        "date": "2026-10-09",
        "prediction": 49.3986,
        "conf_low": 48.0282,
        "conf_high": 50.7691
      },
      {
        "date": "2026-10-10",
        "prediction": 49.4336,
        "conf_low": 48.0544,
        "conf_high": 50.8128
      },
      {
        "date": "2026-10-11",
        "prediction": 49.4407,
        "conf_low": 48.0528,
        "conf_high": 50.8286
      },
      {
        "date": "2026-10-12",
        "prediction": 49.4735,
        "conf_low": 48.077,
        "conf_high": 50.87
      },
      {
        "date": "2026-10-13",
        "prediction": 49.5098,
        "conf_low": 48.1048,
        "conf_high": 50.9149
      },
      {
        "date": "2026-10-14",
        "prediction": 49.521,
        "conf_low": 48.1074,
        "conf_high": 50.9346
      },
      {
        "date": "2026-10-15",
        "prediction": 49.5574,
        "conf_low": 48.1353,
        "conf_high": 50.9795
      }
    ],
    "EUR": [
      {
        "date": "2026-07-18",
        "prediction": 53.9847,
        "conf_low": 53.6091,
        "conf_high": 54.3603
      },
      {
        "date": "2026-07-19",
        "prediction": 54.1414,
        "conf_low": 53.6085,
        "conf_high": 54.6743
      },
      {
        "date": "2026-07-20",
        "prediction": 54.1256,
        "conf_low": 53.4729,
        "conf_high": 54.7782
      },
      {
        "date": "2026-07-21",
        "prediction": 54.1536,
        "conf_low": 53.3997,
        "conf_high": 54.9075
      },
      {
        "date": "2026-07-22",
        "prediction": 54.2235,
        "conf_low": 53.3806,
        "conf_high": 55.0664
      },
      {
        "date": "2026-07-23",
        "prediction": 54.236,
        "conf_low": 53.3125,
        "conf_high": 55.1595
      },
      {
        "date": "2026-07-24",
        "prediction": 54.2821,
        "conf_low": 53.2846,
        "conf_high": 55.2797
      },
      {
        "date": "2026-07-25",
        "prediction": 54.3152,
        "conf_low": 53.2487,
        "conf_high": 55.3817
      },
      {
        "date": "2026-07-26",
        "prediction": 54.2946,
        "conf_low": 53.1635,
        "conf_high": 55.4257
      },
      {
        "date": "2026-07-27",
        "prediction": 54.275,
        "conf_low": 53.0828,
        "conf_high": 55.4672
      },
      {
        "date": "2026-07-28",
        "prediction": 54.3273,
        "conf_low": 53.077,
        "conf_high": 55.5776
      },
      {
        "date": "2026-07-29",
        "prediction": 54.3899,
        "conf_low": 53.084,
        "conf_high": 55.6958
      },
      {
        "date": "2026-07-30",
        "prediction": 54.4055,
        "conf_low": 53.0463,
        "conf_high": 55.7647
      },
      {
        "date": "2026-07-31",
        "prediction": 54.4588,
        "conf_low": 53.0484,
        "conf_high": 55.8693
      },
      {
        "date": "2026-08-01",
        "prediction": 54.4943,
        "conf_low": 53.0344,
        "conf_high": 55.9542
      },
      {
        "date": "2026-08-02",
        "prediction": 54.5461,
        "conf_low": 53.0383,
        "conf_high": 56.0538
      },
      {
        "date": "2026-08-03",
        "prediction": 54.6289,
        "conf_low": 53.0747,
        "conf_high": 56.183
      },
      {
        "date": "2026-08-04",
        "prediction": 54.5897,
        "conf_low": 52.9905,
        "conf_high": 56.1889
      },
      {
        "date": "2026-08-05",
        "prediction": 54.5381,
        "conf_low": 52.8952,
        "conf_high": 56.1811
      },
      {
        "date": "2026-08-06",
        "prediction": 54.5944,
        "conf_low": 52.9088,
        "conf_high": 56.28
      },
      {
        "date": "2026-08-07",
        "prediction": 54.6563,
        "conf_low": 52.929,
        "conf_high": 56.3835
      },
      {
        "date": "2026-08-08",
        "prediction": 54.7311,
        "conf_low": 52.9633,
        "conf_high": 56.499
      },
      {
        "date": "2026-08-09",
        "prediction": 54.8113,
        "conf_low": 53.0038,
        "conf_high": 56.6189
      },
      {
        "date": "2026-08-10",
        "prediction": 54.8818,
        "conf_low": 53.0354,
        "conf_high": 56.7283
      },
      {
        "date": "2026-08-11",
        "prediction": 54.9542,
        "conf_low": 53.0697,
        "conf_high": 56.8387
      },
      {
        "date": "2026-08-12",
        "prediction": 55.0359,
        "conf_low": 53.1141,
        "conf_high": 56.9577
      },
      {
        "date": "2026-08-13",
        "prediction": 55.0327,
        "conf_low": 53.0743,
        "conf_high": 56.9911
      },
      {
        "date": "2026-08-14",
        "prediction": 55.0614,
        "conf_low": 53.067,
        "conf_high": 57.0557
      },
      {
        "date": "2026-08-15",
        "prediction": 55.0314,
        "conf_low": 53.0018,
        "conf_high": 57.061
      },
      {
        "date": "2026-08-16",
        "prediction": 55.0274,
        "conf_low": 52.9631,
        "conf_high": 57.0917
      },
      {
        "date": "2026-08-17",
        "prediction": 55.0581,
        "conf_low": 52.9575,
        "conf_high": 57.1587
      },
      {
        "date": "2026-08-18",
        "prediction": 55.2156,
        "conf_low": 53.0792,
        "conf_high": 57.3519
      },
      {
        "date": "2026-08-19",
        "prediction": 55.1944,
        "conf_low": 53.0229,
        "conf_high": 57.3658
      },
      {
        "date": "2026-08-20",
        "prediction": 55.2247,
        "conf_low": 53.0187,
        "conf_high": 57.4307
      },
      {
        "date": "2026-08-21",
        "prediction": 55.2935,
        "conf_low": 53.0535,
        "conf_high": 57.5336
      },
      {
        "date": "2026-08-22",
        "prediction": 55.3055,
        "conf_low": 53.032,
        "conf_high": 57.5791
      },
      {
        "date": "2026-08-23",
        "prediction": 55.3533,
        "conf_low": 53.0467,
        "conf_high": 57.6599
      },
      {
        "date": "2026-08-24",
        "prediction": 55.3891,
        "conf_low": 53.0499,
        "conf_high": 57.7283
      },
      {
        "date": "2026-08-25",
        "prediction": 55.3686,
        "conf_low": 52.9975,
        "conf_high": 57.7397
      },
      {
        "date": "2026-08-26",
        "prediction": 55.3496,
        "conf_low": 52.947,
        "conf_high": 57.7523
      },
      {
        "date": "2026-08-27",
        "prediction": 55.3954,
        "conf_low": 52.9616,
        "conf_high": 57.8291
      },
      {
        "date": "2026-08-28",
        "prediction": 55.4561,
        "conf_low": 52.9916,
        "conf_high": 57.9206
      },
      {
        "date": "2026-08-29",
        "prediction": 55.4727,
        "conf_low": 52.9778,
        "conf_high": 57.9675
      },
      {
        "date": "2026-08-30",
        "prediction": 55.5232,
        "conf_low": 52.9983,
        "conf_high": 58.048
      },
      {
        "date": "2026-08-31",
        "prediction": 55.5554,
        "conf_low": 53.0009,
        "conf_high": 58.1098
      },
      {
        "date": "2026-09-01",
        "prediction": 55.6071,
        "conf_low": 53.0234,
        "conf_high": 58.1909
      },
      {
        "date": "2026-09-02",
        "prediction": 55.6914,
        "conf_low": 53.0787,
        "conf_high": 58.3041
      },
      {
        "date": "2026-09-03",
        "prediction": 55.6545,
        "conf_low": 53.0132,
        "conf_high": 58.2959
      },
      {
        "date": "2026-09-04",
        "prediction": 55.6035,
        "conf_low": 52.9338,
        "conf_high": 58.2732
      },
      {
        "date": "2026-09-05",
        "prediction": 55.6591,
        "conf_low": 52.9614,
        "conf_high": 58.3569
      },
      {
        "date": "2026-09-06",
        "prediction": 55.7212,
        "conf_low": 52.9957,
        "conf_high": 58.4467
      },
      {
        "date": "2026-09-07",
        "prediction": 55.7978,
        "conf_low": 53.0448,
        "conf_high": 58.5508
      },
      {
        "date": "2026-09-08",
        "prediction": 55.8768,
        "conf_low": 53.0966,
        "conf_high": 58.657
      },
      {
        "date": "2026-09-09",
        "prediction": 55.9472,
        "conf_low": 53.1401,
        "conf_high": 58.7544
      },
      {
        "date": "2026-09-10",
        "prediction": 56.0181,
        "conf_low": 53.1843,
        "conf_high": 58.8519
      },
      {
        "date": "2026-09-11",
        "prediction": 56.1001,
        "conf_low": 53.2399,
        "conf_high": 58.9604
      },
      {
        "date": "2026-09-12",
        "prediction": 56.0973,
        "conf_low": 53.2109,
        "conf_high": 58.9837
      },
      {
        "date": "2026-09-13",
        "prediction": 56.1266,
        "conf_low": 53.2142,
        "conf_high": 59.039
      },
      {
        "date": "2026-09-14",
        "prediction": 56.0956,
        "conf_low": 53.1575,
        "conf_high": 59.0337
      },
      {
        "date": "2026-09-15",
        "prediction": 56.0959,
        "conf_low": 53.1323,
        "conf_high": 59.0595
      },
      {
        "date": "2026-09-16",
        "prediction": 56.1266,
        "conf_low": 53.1356,
        "conf_high": 59.1177
      },
      {
        "date": "2026-09-17",
        "prediction": 56.2841,
        "conf_low": 53.2658,
        "conf_high": 59.3024
      },
      {
        "date": "2026-09-18",
        "prediction": 56.263,
        "conf_low": 53.2178,
        "conf_high": 59.3082
      },
      {
        "date": "2026-09-19",
        "prediction": 56.2933,
        "conf_low": 53.2213,
        "conf_high": 59.3652
      },
      {
        "date": "2026-09-20",
        "prediction": 56.3621,
        "conf_low": 53.2637,
        "conf_high": 59.4605
      },
      {
        "date": "2026-09-21",
        "prediction": 56.3741,
        "conf_low": 53.2494,
        "conf_high": 59.4988
      },
      {
        "date": "2026-09-22",
        "prediction": 56.4219,
        "conf_low": 53.2711,
        "conf_high": 59.5726
      },
      {
        "date": "2026-09-23",
        "prediction": 56.4577,
        "conf_low": 53.2811,
        "conf_high": 59.6342
      },
      {
        "date": "2026-09-24",
        "prediction": 56.4372,
        "conf_low": 53.2352,
        "conf_high": 59.6392
      },
      {
        "date": "2026-09-25",
        "prediction": 56.4181,
        "conf_low": 53.1909,
        "conf_high": 59.6454
      },
      {
        "date": "2026-09-26",
        "prediction": 56.464,
        "conf_low": 53.2117,
        "conf_high": 59.7162
      },
      {
        "date": "2026-09-27",
        "prediction": 56.5247,
        "conf_low": 53.2476,
        "conf_high": 59.8018
      },
      {
        "date": "2026-09-28",
        "prediction": 56.5413,
        "conf_low": 53.2396,
        "conf_high": 59.843
      },
      {
        "date": "2026-09-29",
        "prediction": 56.5918,
        "conf_low": 53.2656,
        "conf_high": 59.918
      },
      {
        "date": "2026-09-30",
        "prediction": 56.6241,
        "conf_low": 53.2736,
        "conf_high": 59.9745
      },
      {
        "date": "2026-10-01",
        "prediction": 56.6758,
        "conf_low": 53.3013,
        "conf_high": 60.0504
      },
      {
        "date": "2026-10-02",
        "prediction": 56.7601,
        "conf_low": 53.3616,
        "conf_high": 60.1586
      },
      {
        "date": "2026-10-03",
        "prediction": 56.7232,
        "conf_low": 53.3009,
        "conf_high": 60.1455
      },
      {
        "date": "2026-10-04",
        "prediction": 56.6721,
        "conf_low": 53.2262,
        "conf_high": 60.118
      },
      {
        "date": "2026-10-05",
        "prediction": 56.7278,
        "conf_low": 53.2584,
        "conf_high": 60.1971
      },
      {
        "date": "2026-10-06",
        "prediction": 56.7899,
        "conf_low": 53.2972,
        "conf_high": 60.2825
      },
      {
        "date": "2026-10-07",
        "prediction": 56.8664,
        "conf_low": 53.3507,
        "conf_high": 60.3822
      },
      {
        "date": "2026-10-08",
        "prediction": 56.9455,
        "conf_low": 53.4067,
        "conf_high": 60.4842
      },
      {
        "date": "2026-10-09",
        "prediction": 57.0159,
        "conf_low": 53.4543,
        "conf_high": 60.5775
      },
      {
        "date": "2026-10-10",
        "prediction": 57.0867,
        "conf_low": 53.5024,
        "conf_high": 60.671
      },
      {
        "date": "2026-10-11",
        "prediction": 57.1688,
        "conf_low": 53.5619,
        "conf_high": 60.7756
      },
      {
        "date": "2026-10-12",
        "prediction": 57.166,
        "conf_low": 53.5367,
        "conf_high": 60.7952
      },
      {
        "date": "2026-10-13",
        "prediction": 57.1953,
        "conf_low": 53.5438,
        "conf_high": 60.8468
      },
      {
        "date": "2026-10-14",
        "prediction": 57.1643,
        "conf_low": 53.4906,
        "conf_high": 60.8379
      },
      {
        "date": "2026-10-15",
        "prediction": 57.1645,
        "conf_low": 53.4689,
        "conf_high": 60.8602
      }
    ]
  }
}